MANIFEST.in
README.md
setup.py
nboost/__init__.py
nboost/__main__.py
nboost/__version__.py
nboost/cli.py
nboost/compat.py
nboost/database.py
nboost/defaults.py
nboost/delegates.py
nboost/exceptions.py
nboost/helpers.py
nboost/logger.py
nboost/maps.py
nboost/proxy.py
nboost/translators.py
nboost.egg-info/PKG-INFO
nboost.egg-info/SOURCES.txt
nboost.egg-info/dependency_links.txt
nboost.egg-info/entry_points.txt
nboost.egg-info/requires.txt
nboost.egg-info/top_level.txt
nboost/indexers/__init__.py
nboost/indexers/__main__.py
nboost/indexers/base.py
nboost/indexers/cli.py
nboost/indexers/defaults.py
nboost/indexers/es.py
nboost/indexers/solr.py
nboost/plugins/__init__.py
nboost/plugins/debug.py
nboost/plugins/prerank.py
nboost/plugins/qa/__init__.py
nboost/plugins/qa/base.py
nboost/plugins/qa/distilbert.py
nboost/plugins/rerank/__init__.py
nboost/plugins/rerank/base.py
nboost/plugins/rerank/onnxbert.py
nboost/plugins/rerank/shuffle.py
nboost/plugins/rerank/transformers.py
nboost/plugins/rerank/use.py
nboost/resources/travel.csv
nboost/resources/frontend/404.html
nboost/resources/frontend/bindings.js
nboost/resources/frontend/index.html
nboost/resources/frontend/main.css