Metadata-Version: 2.1
Name: nboost
Version: 0.3.9
Summary: Nboost is a scalable, search-api-boosting platform for developing and deploying automated SOTA models more relevant search results.
Home-page: https://github.com/koursaros-ai/nboost
Author: Koursaros
Author-email: cole.thienes@gmail.com
License: Apache 2.0
Keywords: elasticsearch,distributed,cloud-native,neural,inference
Platform: UNKNOWN
Classifier: Intended Audience :: Education
Classifier: Intended Audience :: Science/Research
Classifier: Intended Audience :: Developers
Classifier: Topic :: Scientific/Engineering :: Artificial Intelligence
Classifier: Topic :: Internet :: WWW/HTTP :: Indexing/Search
Classifier: Topic :: Scientific/Engineering
Classifier: Topic :: Scientific/Engineering :: Mathematics
Classifier: Topic :: Software Development
Classifier: Topic :: Software Development :: Libraries
Classifier: Topic :: Software Development :: Libraries :: Python Modules
Classifier: License :: OSI Approved :: Apache Software License
Classifier: Programming Language :: Python :: 3.5
Classifier: Programming Language :: Python :: 3.6
Classifier: Programming Language :: Python :: 3.7
Provides-Extra: pt
Provides-Extra: tf
Provides-Extra: all
